LICENSE
MANIFEST.in
README.rst
pyproject.toml
setup.cfg
setup.py
zuqa/__init__.py
zuqa/base.py
zuqa/events.py
zuqa/middleware.py
zuqa/processors.py
zuqa/traces.py
zuqa/version.py
zuqa/conf/__init__.py
zuqa/conf/constants.py
zuqa/context/__init__.py
zuqa/context/base.py
zuqa/context/contextvars.py
zuqa/context/threadlocal.py
zuqa/contrib/__init__.py
zuqa/contrib/paste.py
zuqa/contrib/aiohttp/__init__.py
zuqa/contrib/aiohttp/middleware.py
zuqa/contrib/aiohttp/utils.py
zuqa/contrib/asyncio/__init__.py
zuqa/contrib/asyncio/traces.py
zuqa/contrib/celery/__init__.py
zuqa/contrib/django/__init__.py
zuqa/contrib/django/apps.py
zuqa/contrib/django/client.py
zuqa/contrib/django/context_processors.py
zuqa/contrib/django/handlers.py
zuqa/contrib/django/utils.py
zuqa/contrib/django/celery/__init__.py
zuqa/contrib/django/celery/models.py
zuqa/contrib/django/management/__init__.py
zuqa/contrib/django/management/commands/__init__.py
zuqa/contrib/django/management/commands/elasticapm.py
zuqa/contrib/django/middleware/__init__.py
zuqa/contrib/django/middleware/wsgi.py
zuqa/contrib/flask/__init__.py
zuqa/contrib/flask/utils.py
zuqa/contrib/opentracing/__init__.py
zuqa/contrib/opentracing/span.py
zuqa/contrib/opentracing/tracer.py
zuqa/contrib/pylons/__init__.py
zuqa/contrib/rq/__init__.py
zuqa/contrib/starlette/__init__.py
zuqa/contrib/starlette/utils.py
zuqa/contrib/tornado/__init__.py
zuqa/contrib/tornado/utils.py
zuqa/contrib/twisted/__init__.py
zuqa/contrib/zerorpc/__init__.py
zuqa/handlers/__init__.py
zuqa/handlers/logbook.py
zuqa/handlers/logging.py
zuqa/handlers/structlog.py
zuqa/instrumentation/__init__.py
zuqa/instrumentation/control.py
zuqa/instrumentation/register.py
zuqa/instrumentation/packages/__init__.py
zuqa/instrumentation/packages/base.py
zuqa/instrumentation/packages/botocore.py
zuqa/instrumentation/packages/cassandra.py
zuqa/instrumentation/packages/dbapi2.py
zuqa/instrumentation/packages/elasticsearch.py
zuqa/instrumentation/packages/jinja2.py
zuqa_agent_python.egg-info/PKG-INFO
zuqa_agent_python.egg-info/SOURCES.txt
zuqa_agent_python.egg-info/dependency_links.txt
zuqa_agent_python.egg-info/entry_points.txt
zuqa_agent_python.egg-info/not-zip-safe
zuqa_agent_python.egg-info/requires.txt
zuqa_agent_python.egg-info/top_level.txt