Metadata-Version: 2.1
Name: zuqa-agent-python
Version: 1.0.0a1
Summary: The official Python module for zuQA
Home-page: https://github.com/zukatechnologies/zuqa-agent-python
Author: Zuka Technologies, Inc
License: BSD
Platform: UNKNOWN
Classifier: Intended Audience :: Developers
Classifier: Operating System :: OS Independent
Classifier: Topic :: Software Development
Classifier: Development Status :: 3 - Alpha
Classifier: Programming Language :: Python
Classifier: Programming Language :: Python :: 2.7
Classifier: Programming Language :: Python :: 3.5
Classifier: Programming Language :: Python :: 3.6
Classifier: Programming Language :: Python :: 3.7
Classifier: Programming Language :: Python :: 3.8
Classifier: Programming Language :: Python :: Implementation :: CPython
Classifier: Programming Language :: Python :: Implementation :: PyPy
Classifier: License :: OSI Approved :: BSD License
Requires-Python: >=2.7, !=3.0.*, !=3.1.*, !=3.2.*, !=3.3.*, !=3.4.*, <4
Provides-Extra: tests
Provides-Extra: flask
Provides-Extra: aiohttp
Provides-Extra: tornado
Provides-Extra: starlette
Provides-Extra: opentracing
